verilog/branch.v
module branch(
    input  [31:0] a,
    input  [31:0] b,
    input  [3:0] fn,
    output reg taken
);

always @(*) begin
    case (fn)
        4'h0: taken = 0;
        4'h1: taken = (a == b);
        4'h2: taken = (a <  b);
        4'h3: taken = (a <= b);

        4'h5: taken = (a == 32'd0);
        4'h6: taken = (a <  32'd0);
        4'h7: taken = (a <= 32'd0);

        4'h8: taken = 1;
        4'h9: taken = (a != b);
        4'hA: taken = (a >= b);
        4'hB: taken = (a >  b);

        4'hD: taken = (a != 32'd0);
        4'hE: taken = (a >= 32'd0);
        4'hF: taken = (a >  32'd0);

        default: taken = 0;
    endcase
end

endmodule

verilog/cmp.v
module cmp(
    input [31:0] a,
    input [31:0] b,
    input [3:0] fn,
    output reg [31:0] result
);

always @(*) begin
    case (fn)
        4'h0: result = 32'd0;                         // F
        4'h1: result = (a == b) ? 32'd1 : 32'd0;      // EQ
        4'h2: result = (a <  b) ? 32'd1 : 32'd0;      // LT
        4'h3: result = (a <= b) ? 32'd1 : 32'd0;      // LTE
        4'h8: result = 32'd1;                         // T
        4'h9: result = (a != b) ? 32'd1 : 32'd0;      // NE
        4'hA: result = (a >= b) ? 32'd1 : 32'd0;      // GTE
        4'hB: result = (a >  b) ? 32'd1 : 32'd0;      // GT
        default: result = 32'd0;
    endcase
end

endmodule

verilog/alu.v
module alu(
    input  [31:0] a,
    input  [31:0] b,
    input  [3:0] fn,
    output reg [31:0] result
);

always @(*) begin
    case (fn)
        4'h0: result = a + b;
        4'h1: result = a - b;
        4'h4: result = a & b;
        4'h5: result = a | b;
        4'h6: result = a ^ b;
        4'hC: result = ~(a & b);
        4'hD: result = ~(a | b);
        4'hE: result = ~(a ^ b);
        default: result = 32'd0;
    endcase
end

endmodule

verilog/regfile.v
module regfile(
    input clk,
    input reset,

    input [3:0] rs1,
    input [3:0] rs2,
    input [3:0] rd,

    input write_enable,
    input [31:0] write_data,

    output [31:0] rs1_val,
    output [31:0] rs2_val
);

reg [31:0] regs [0:15];
integer i;

assign rs1_val = regs[rs1];
assign rs2_val = regs[rs2];

always @(posedge clk) begin
    if (reset) begin
        for (i = 0; i < 16; i = i + 1) begin
            regs[i] <= 32'd0;
        end
    end else if (write_enable) begin
        regs[rd] <= write_data;
    end
end

endmodule

verilog/cpu.v
module cpu(
    input clk,
    input reset,
    input [3:0] KEY,
    input [9:0] SW,
    output [9:0] LEDR
);

reg [31:0] pc;
reg [31:0] imem [0:255];
reg [31:0] dmem [0:255];

integer j;

reg [9:0] ledr_reg;
assign LEDR = ledr_reg;

//Current instruction
wire [31:0] instr;
//word-aligned instruction fetch
assign instr = imem[pc[9:2]];

// Decode fields
wire [3:0] opcode;
wire [3:0] fn;
wire [15:0] imm;
wire [3:0] rd;
wire [3:0] normal_rs1;
wire [3:0] normal_rs2;

assign opcode = instr[3:0];
assign fn = instr[7:4];
assign imm = instr[23:8];
assign normal_rs2 = instr[23:20];
assign normal_rs1 = instr[27:24];
assign rd = instr[31:28];

//Sign-extended immediate
wire [31:0] imm_sext;
assign imm_sext = {{16{imm[15]}}, imm};

wire branch_or_store;
assign branch_or_store = (opcode == 4'h6 || opcode == 4'h5);

wire [3:0] read_rs1;
wire [3:0] read_rs2;

assign read_rs1 = branch_or_store ? instr[31:28] : normal_rs1;
assign read_rs2 = branch_or_store ? instr[27:24] : normal_rs2;

// Register file wires
wire [31:0] rs1_val;
wire [31:0] rs2_val;

reg write_enable;
reg [31:0] write_data;

regfile rf0(
    .clk(clk),
    .reset(reset),

    .rs1(read_rs1),
    .rs2(read_rs2),
    .rd(rd),

    .write_enable(write_enable),
    .write_data(write_data),

    .rs1_val(rs1_val),
    .rs2_val(rs2_val)
);

//LW/SW
wire [31:0] addr;
wire [7:0] dmem_index;

assign addr = rs1_val + imm_sext;
assign dmem_index = addr[9:2];

//ALU
wire [31:0] alu_b;
wire [31:0] alu_result;

assign alu_b = (opcode == 4'h8) ? imm_sext : rs2_val;

alu alu0(
    .a(rs1_val),
    .b(alu_b),
    .fn(fn),
    .result(alu_result)
);

//CMP
wire [31:0] cmp_b;
wire [31:0] cmp_result;

assign cmp_b = (opcode == 4'hA) ? imm_sext : rs2_val;

cmp cmp0(
    .a(rs1_val),
    .b(cmp_b),
    .fn(fn),
    .result(cmp_result)
);

//Branch/PC control
wire branch_taken;
reg [31:0] next_pc;

branch branch0(
    .a(rs1_val),
    .b(rs2_val),
    .fn(fn),
    .taken(branch_taken)
);

task load_mif;
    input [1023:0] filename;

    integer file;
    integer code;
    integer addr;
    integer data;
    reg [1023:0] line;

    begin
        file = $fopen(filename, "r");

        if (file == 0) begin
            $display("ERROR: could not open %s", filename);
        end else begin
            while (!$feof(file)) begin
                code = $fgets(line, file);

                if ($sscanf(line, "%h: %h;", addr, data) == 2) begin
                    imem[addr] = data;
                end
            end

            $fclose(file);
        end
    end
endtask

//Initialize memory
initial begin
    for (j = 0; j < 256; j = j + 1) begin
        imem[j] = 32'h00000000;
        dmem[j] = 32'h00000000;
    end

    ledr_reg = 10'b0;

    //Load assembler output here
    //$readmemh("program.mif", imem);
    load_mif("program.mif");
end

//Combinational control logic
always @(*) begin
    write_enable = 0;
    write_data = 32'd0;
    next_pc = pc + 4;

    case (opcode)

        4'h0: begin
            //ALUR
            write_enable = 1;
            write_data = alu_result;
        end

        4'h8: begin
            //ALUI and MVHI
            write_enable = 1;

            if (fn == 4'hB) begin
                write_data = {imm, 16'b0}; // MVHI
            end else begin
                write_data = alu_result;
            end
        end

        4'h2: begin
            //CMPR
            write_enable = 1;
            write_data = cmp_result;
        end

        4'hA: begin
            //CMPI
            write_enable = 1;
            write_data = cmp_result;
        end

        4'h9: begin
            //LW
            write_enable = 1;

            if (addr == 32'hF0000010) begin
                write_data = {28'd0, KEY};
            end else if (addr == 32'hF0000014) begin
                write_data = {22'd0, SW};
            end else begin
                write_data = dmem[dmem_index];
            end
        end
        4'h6: begin
            if (branch_taken) begin
                next_pc = pc + 4 + (imm_sext << 2);
            end
        end

        4'hB: begin
            // JAL
            if (fn == 4'h0) begin
                write_enable = 1;
                write_data = pc + 4;
                next_pc = rs1_val + (imm_sext << 2);
            end
        end

        default: begin
            // do nothing
        end

    endcase
end
always @(posedge clk) begin
    if (reset) begin
        pc <= 32'h40;
        ledr_reg <= 10'b0;
    end else begin
        //SW
        if (opcode == 4'h5) begin
            if (addr == 32'hF0000004) begin
                ledr_reg <= rs2_val[9:0];
            end else begin
                dmem[dmem_index] <= rs2_val;
            end
        end
        pc <= next_pc;
        $display("PC=%h instr=%h op=%h fn=%h rd=R%0d rs1=R%0d(%0d) rs2=R%0d(%0d) imm=%h write=%b wdata=%0d LEDR=%b",
            pc, instr, opcode, fn, rd, read_rs1, rs1_val, read_rs2, rs2_val,
            imm, write_enable, write_data, LEDR);
    end
end

endmodule

verilog/pipeline_tb.v
module pipeline_tb;

  reg clk = 0;
  reg reset = 1;
  reg [3:0] KEY = 4'b0000;
  reg [9:0] SW = 10'b0000000000;
  wire [9:0] LEDR;

  cpu uut (
    .clk(clk),
    .reset(reset),
    .KEY(KEY),
    .SW(SW),
    .LEDR(LEDR)
  );

  always #5 clk = ~clk;

  initial begin
    $dumpfile("cpu.vcd");
    $dumpvars(0, pipeline_tb);

    #10 reset = 0;

    #300;
    $finish;
  end

endmodule

cpu.vcd
$date
	Wed May 13 13:08:50 2026
$end
$version
	Icarus Verilog
$end
$timescale
	1s
$end
$scope module pipeline_tb $end
$var wire 10 ! LEDR [9:0] $end
$var reg 4 " KEY [3:0] $end
$var reg 10 # SW [9:0] $end
$var reg 1 $ clk $end
$var reg 1 % reset $end
$scope module uut $end
$var wire 4 & KEY [3:0] $end
$var wire 10 ' LEDR [9:0] $end
$var wire 10 ( SW [9:0] $end
$var wire 1 ) branch_or_store $end
$var wire 1 $ clk $end
$var wire 32 * instr [31:0] $end
$var wire 1 % reset $end
$var wire 32 + rs2_val [31:0] $end
$var wire 32 , rs1_val [31:0] $end
$var wire 4 - read_rs2 [3:0] $end
$var wire 4 . read_rs1 [3:0] $end
$var wire 4 / rd [3:0] $end
$var wire 4 0 opcode [3:0] $end
$var wire 4 1 normal_rs2 [3:0] $end
$var wire 4 2 normal_rs1 [3:0] $end
$var wire 32 3 imm_sext [31:0] $end
$var wire 16 4 imm [15:0] $end
$var wire 4 5 fn [3:0] $end
$var wire 8 6 dmem_index [7:0] $end
$var wire 32 7 cmp_result [31:0] $end
$var wire 32 8 cmp_b [31:0] $end
$var wire 1 9 branch_taken $end
$var wire 32 : alu_result [31:0] $end
$var wire 32 ; alu_b [31:0] $end
$var wire 32 < addr [31:0] $end
$var reg 10 = ledr_reg [9:0] $end
$var reg 32 > next_pc [31:0] $end
$var reg 32 ? pc [31:0] $end
$var reg 32 @ write_data [31:0] $end
$var reg 1 A write_enable $end
$var integer 32 B j [31:0] $end
$scope module alu0 $end
$var wire 32 C b [31:0] $end
$var wire 4 D fn [3:0] $end
$var wire 32 E a [31:0] $end
$var reg 32 F result [31:0] $end
$upscope $end
$scope module branch0 $end
$var wire 4 G fn [3:0] $end
$var wire 32 H b [31:0] $end
$var wire 32 I a [31:0] $end
$var reg 1 9 taken $end
$upscope $end
$scope module cmp0 $end
$var wire 32 J b [31:0] $end
$var wire 4 K fn [3:0] $end
$var wire 32 L a [31:0] $end
$var reg 32 M result [31:0] $end
$upscope $end
$scope module rf0 $end
$var wire 1 $ clk $end
$var wire 4 N rd [3:0] $end
$var wire 1 % reset $end
$var wire 4 O rs1 [3:0] $end
$var wire 32 P rs1_val [31:0] $end
$var wire 4 Q rs2 [3:0] $end
$var wire 32 R rs2_val [31:0] $end
$var wire 32 S write_data [31:0] $end
$var wire 1 A write_enable $end
$var integer 32 T i [31:0] $end
$upscope $end
$scope task load_mif $end
$var reg 1024 U filename [1023:0] $end
$var reg 1024 V line [1023:0] $end
$var integer 32 W addr [31:0] $end
$var integer 32 X code [31:0] $end
$var integer 32 Y data [31:0] $end
$var integer 32 Z file [31:0] $end
$upscope $end
$upscope $end
$upscope $end
$enddefinitions $end
$comment Show the parameter values. $end
$dumpall
$end
#0
$dumpvars
b10000000000000000000000000000011 Z
b10000000000001101111000001000 Y
b0 X
b1110 W
b100010101001110010001000011101100001010 V
b111000001110010011011110110011101110010011000010110110100101110011011010110100101100110 U
bx T
b0 S
bx R
bx Q
bx P
bx O
bx N
bx M
bx L
bx K
bx J
bx I
bx H
bx G
bx F
bx E
bx D
bx C
b100000000 B
0A
b0 @
bx ?
bx >
b0 =
bx <
bx ;
bx :
x9
bx 8
bx 7
bx 6
bx 5
bx 4
bx 3
bx 2
bx 1
bx 0
bx /
bx .
bx -
bx ,
bx +
bx *
x)
b0 (
b0 '
b0 &
1%
0$
b0 #
b0 "
b0 !
$end
#5
b10 6
b1010 :
b1010 F
b1010 <
b0 ,
b0 E
b0 I
b0 L
b0 P
b0 8
b0 J
b0 +
b0 H
b0 R
0)
b1010 ;
b1010 C
09
b0 7
b0 M
b1010 3
b1010 @
b1010 S
1A
b0 .
b0 O
b0 -
b0 Q
b1000 0
b0 5
b0 D
b0 G
b0 K
b1010 4
b0 1
b0 2
b10 /
b10 N
b100000000000000000101000001000 *
b1000100 >
b1000000 ?
b10000 T
1$
#10
0$
0%
#15
b11 /
b11 N
b110000000000000000101000001000 *
b1001000 >
b1010 @
b1010 S
1A
b1000100 ?
1$
#20
0$
#25
b1010 8
b1010 J
b1010 +
b1010 H
b1010 R
b11 -
b11 Q
b1010 ,
b1010 E
b1010 I
b1010 L
b1010 P
1)
b1010 ;
b1010 C
b0 :
b0 F
19
b1 7
b1 M
b1011 <
b1 3
b10 .
b10 O
b110 0
b1 5
b1 D
b1 G
b1 K
b1 4
b11 2
b10 /
b10 N
b100011000000000000000100010110 *
b1010000 >
b0 @
b0 S
0A
b1001000 ?
1$
#30
0$
#35
b0 8
b0 J
b110111 6
b11011110 @
b11011110 S
b0 ,
b0 E
b0 I
b0 L
b0 P
b0 +
b0 H
b0 R
0)
b11011110 ;
b11011110 C
b11011110 :
b11011110 F
09
b0 7
b0 M
b11011110 <
b11011110 3
1A
b0 .
b0 O
b0 -
b0 Q
b1000 0
b0 5
b0 D
b0 G
b0 K
b11011110 4
b0 2
b1 /
b1 N
b10000000000001101111000001000 *
b1010100 >
b1010000 ?
1$
#40
0$
#45
b0 :
b0 F
b0 6
b0 ;
b0 C
b0 <
b0 3
b0 0
b0 4
b0 /
b0 N
b0 *
b1011000 >
b0 @
b0 S
1A
b1010100 ?
1$
#50
0$
#55
b1011100 >
1A
b1011000 ?
1$
#60
0$
#65
b1100000 >
1A
b1011100 ?
1$
#70
0$
#75
b1100100 >
1A
b1100000 ?
1$
#80
0$
#85
b1101000 >
1A
b1100100 ?
1$
#90
0$
#95
b1101100 >
1A
b1101000 ?
1$
#100
0$
#105
b1110000 >
1A
b1101100 ?
1$
#110
0$
#115
b1110100 >
1A
b1110000 ?
1$
#120
0$
#125
b1111000 >
1A
b1110100 ?
1$
#130
0$
#135
b1111100 >
1A
b1111000 ?
1$
#140
0$
#145
b10000000 >
1A
b1111100 ?
1$
#150
0$
#155
b10000100 >
1A
b10000000 ?
1$
#160
0$
#165
b10001000 >
1A
b10000100 ?
1$
#170
0$
#175
b10001100 >
1A
b10001000 ?
1$
#180
0$
#185
b10010000 >
1A
b10001100 ?
1$
#190
0$
#195
b10010100 >
1A
b10010000 ?
1$
#200
0$
#205
b10011000 >
1A
b10010100 ?
1$
#210
0$
#215
b10011100 >
1A
b10011000 ?
1$
#220
0$
#225
b10100000 >
1A
b10011100 ?
1$
#230
0$
#235
b10100100 >
1A
b10100000 ?
1$
#240
0$
#245
b10101000 >
1A
b10100100 ?
1$
#250
0$
#255
b10101100 >
1A
b10101000 ?
1$
#260
0$
#265
b10110000 >
1A
b10101100 ?
1$
#270
0$
#275
b10110100 >
1A
b10110000 ?
1$
#280
0$
#285
b10111000 >
1A
b10110100 ?
1$
#290
0$
#295
b10111100 >
1A
b10111000 ?
1$
#300
0$
#305
b11000000 >
1A
b10111100 ?
1$
